{
  "name": "kemalettin tuzcu",
  "persona": "Dengeli Harcamacı ⚖️",
  "ratings": {
    "gaming": 3,
    "food": 3,
    "kira": 3,
    "housing": 3,
    "transport": 3,
    "bills": 3
  },
  "generatedExpenses": [
    {
      "name": "Epic Games Purchases",
      "amount": 452,
      "date": 2,
      "category": "gaming"
    },
    {
      "name": "Steam Games",
      "amount": 645,
      "date": 2,
      "category": "gaming"
    },
    {
      "name": "BP Fuel Station",
      "amount": 3358,
      "date": 3,
      "category": "transport"
    },
    {
      "name": "Daire Kira Bedeli",
      "amount": 14556,
      "date": 5,
      "category": "kira"
    },
    {
      "name": "GetirYemek",
      "amount": 577,
      "date": 9,
      "category": "food"
    },
    {
      "name": "BiTaksi",
      "amount": 261,
      "date": 12,
      "category": "transport"
    },
    {
      "name": "Spotify Duo",
      "amount": 179,
      "date": 13,
      "category": "bills"
    },
    {
      "name": "Disney+ Monthly",
      "amount": 225,
      "date": 14,
      "category": "bills"
    },
    {
      "name": "Emlak Vergisi Odemesi",
      "amount": 3625,
      "date": 16,
      "category": "barinma"
    },
    {
      "name": "Site Aidati",
      "amount": 2177,
      "date": 18,
      "category": "barinma"
    },
    {
      "name": "iCloud Saklama Alani",
      "amount": 95,
      "date": 22,
      "category": "bills"
    },
    {
      "name": "PlayStation Network",
      "amount": 625,
      "date": 26,
      "category": "gaming"
    },
    {
      "name": "Trendyol Yemek",
      "amount": 542,
      "date": 26,
      "category": "food"
    },
    {
      "name": "Starbucks Coffee",
      "amount": 254,
      "date": 27,
      "category": "food"
    },
    {
      "name": "Istanbulkart Yukleme",
      "amount": 448,
      "date": 27,
      "category": "transport"
    },
    {
      "name": "Koctas Yapi Market",
      "amount": 1925,
      "date": 28,
      "category": "barinma"
    }
  ]
}